exdir/__init__.py
exdir/_version.py
exdir/core/__init__.py
exdir/core/attribute.py
exdir/core/constants.py
exdir/core/dataset.py
exdir/core/exdir_file.py
exdir/core/exdir_object.py
exdir/core/group.py
exdir/core/mode.py
exdir/core/raw.py
exdir/core/validation.py
exdir/plugin_interface/__init__.py
exdir/plugin_interface/plugin_interface.py
exdir/plugins/__init__.py
exdir/plugins/git_lfs.py
exdir/plugins/numpy_attributes.py
exdir/plugins/quantities.py
exdir/static/index.js
exdir/utils/__init__.py
exdir/utils/display.py
exdir/utils/path.py
exdir-0.5.0.1.data/data/etc/jupyter/jupyter_notebook_config.d/exdir.json
exdir-0.5.0.1.data/data/etc/jupyter/nbconfig/notebook.d/exdir.json
exdir-0.5.0.1.data/data/share/jupyter/nbextensions/exdir/index.js
exdir-0.5.0.1.dist-info/LICENSE
exdir-0.5.0.1.dist-info/METADATA
exdir-0.5.0.1.dist-info/WHEEL
exdir-0.5.0.1.dist-info/top_level.txt
exdir-0.5.0.1.dist-info/RECORD
